MANIFEST.in
setup.py
bin/p3_amazonjp_sales_report
p3_amazon_jp_tool/__init__.py
p3_amazon_jp_tool/sales_report.py
p3_amazon_jp_tool.egg-info/PKG-INFO
p3_amazon_jp_tool.egg-info/SOURCES.txt
p3_amazon_jp_tool.egg-info/dependency_links.txt
p3_amazon_jp_tool.egg-info/requires.txt
p3_amazon_jp_tool.egg-info/top_level.txt
p3_amazon_jp_tool/data/amazon_uni.csv