Metadata-Version: 1.1
Name: p3-amazon-jp-tool
Version: 0.1.28
Summary: Amazon JP Sales Reports
Home-page: https://bitbucket.com/bealox/p3_amazon_jp_report
Author: Andy Hsieh
Author-email: andy.hsieh@hotmail.com
License: LICENSE.txt
Platform: UNKNOWN
Classifier: Programming Language :: Python
Classifier: Programming Language :: Python :: 3
Classifier: Programming Language :: Python :: 3.6
Classifier: Environment :: Other Environment
Classifier: Intended Audience :: Developers
Classifier: License :: OSI Approved :: MIT License
Classifier: Operating System :: OS Independent
